anna_unittasks/__init__.py
anna_unittasks/click.py
anna_unittasks/config.py
anna_unittasks/current_url.py
anna_unittasks/fail.py
anna_unittasks/hover.py
anna_unittasks/select.py
anna_unittasks/send_keys.py
anna_unittasks/submit.py
anna_unittasks/switch_to.py
anna_unittasks/wait.py
anna_unittasks/iframe/__init__.py
anna_unittasks/iframe/click.py
anna_unittasks/iframe/hover.py
anna_unittasks/iframe/send_keys.py
anna_unittasks/iframe/submit.py
anna_unittasks/iframe/wait.py
anna_unittasks-1.0.13.dist-info/METADATA
anna_unittasks-1.0.13.dist-info/WHEEL
anna_unittasks-1.0.13.dist-info/top_level.txt
anna_unittasks-1.0.13.dist-info/RECORD
