Metadata-Version: 2.1
Name: anna-unittasks
Version: 1.0.13
Summary: anna task package for unittesting
Home-page: https://github.com/patrikpihlstrom/anna-unittasks
Author: Patrik Pihlstrom
Author-email: patrik.pihlstrom@gmail.com
License: UNKNOWN
Platform: UNKNOWN
Requires-Dist: anna-lib
